debounce_redis_guard/__init__.py
debounce_redis_guard/config.toml.py
debounce_redis_guard/common/__init__.py
debounce_redis_guard/common/commonModel.py
debounce_redis_guard/config/__init__.py
debounce_redis_guard/config/redis.py
debounce_redis_guard/src/__init__.py
debounce_redis_guard/src/debouncer.py
tests/__init__.py
tests/http_module.py
tests/test_http_module.py
debounce_redis_guard-0.0.8.dist-info/LICENSE
debounce_redis_guard-0.0.8.dist-info/METADATA
debounce_redis_guard-0.0.8.dist-info/WHEEL
debounce_redis_guard-0.0.8.dist-info/top_level.txt
debounce_redis_guard-0.0.8.dist-info/RECORD
