Metadata-Version: 2.1
Name: debounce-redis-guard
Version: 0.0.8
Summary: A Python library for debouncing requests with support for multiple workers.
Home-page: https://github.com/cdeepana/debounce_redis_guard
Author: Chathura Deepana Herath
Author-email: chathuradeepana7@gmail.com
Classifier: Programming Language :: Python :: 3
Classifier: License :: OSI Approved :: MIT License
Classifier: Development Status :: 4 - Beta
Requires-Python: >=3.6
License-File: LICENSE
